mysqltotsv/__init__.py
mysqltotsv-0.1.4.data/scripts/mysql-to-tsv.py
tests/__init__.py
tests/basic.py
mysqltotsv-0.1.4.dist-info/LICENSE
mysqltotsv-0.1.4.dist-info/METADATA
mysqltotsv-0.1.4.dist-info/WHEEL
mysqltotsv-0.1.4.dist-info/top_level.txt
mysqltotsv-0.1.4.dist-info/RECORD
