Metadata-Version: 2.1
Name: mysqltotsv
Version: 0.1.4
Summary: Tool for conversion of MySQL dumps to TSV format
Home-page: https://wsdookadr.github.io/posts/
Author: Stefan Corneliu Petrea
Author-email: stefan.petrea@gmail.com
License: UNKNOWN
Platform: UNKNOWN
Classifier: Programming Language :: Python :: 3
Classifier: License :: OSI Approved :: MIT License
Classifier: Operating System :: OS Independent
Requires-Python: >=3.5
License-File: LICENSE
Requires-Dist: lark-parser >=0.11.1
Provides-Extra: lark-parser
Requires-Dist: regex ; extra == 'lark-parser'
